cadcadgolem/__init__.py
cadcadgolem/async_isolation.py
cadcadgolem/golem_embassy.py
cadcadgolem/remote/Dockerfile
cadcadgolem/remote/__init__.py
cadcadgolem/remote/golem-diplomat.py
cadcadgolem/remote/run-golem-diplomat.sh
cadcadgolem-0.2.2.dist-info/LICENSE
cadcadgolem-0.2.2.dist-info/METADATA
cadcadgolem-0.2.2.dist-info/WHEEL
cadcadgolem-0.2.2.dist-info/top_level.txt
cadcadgolem-0.2.2.dist-info/RECORD
