Metadata-Version: 2.1
Name: cadcadgolem
Version: 0.2.2
Summary: A cadCAD workload dispatcher to the Golem network
Home-page: https://github.com/rogervs/cadcadgolem
Author: Roger van Schie
Author-email: rogervs@protonmail.com
License: UNKNOWN
Platform: UNKNOWN
Classifier: Development Status :: 3 - Alpha
Classifier: Programming Language :: Python :: 3
Classifier: Intended Audience :: Science/Research
Classifier: License :: OSI Approved :: MIT License
Classifier: Operating System :: OS Independent
Requires-Python: >=3.8.5
Requires-Dist: cadcad
Requires-Dist: yapapi
